groupc_extended_df/__init__.py
groupc_extended_df/setup.py
extendeddataframeteamc-0.2.dist-info/METADATA
extendeddataframeteamc-0.2.dist-info/WHEEL
extendeddataframeteamc-0.2.dist-info/top_level.txt
extendeddataframeteamc-0.2.dist-info/RECORD
