Metadata-Version: 2.1
Name: extendeddataframeteamc
Version: 0.2
Summary: Extends the pandas dataframe with new functionalities. 
Home-page: https://github.com/juliangaona/fairdetect_c
Author: Team_C_GMBD_2022_IE_UNIVERSITY
Author-email: julian.gaona.gonzalez@gmail.com
License: GNU General Public License v3.0 
Platform: UNKNOWN
